ez_setup.py
setup.py
urlrelay.py
tests/test_urlrelay.py
urlrelay.egg-info/PKG-INFO
urlrelay.egg-info/SOURCES.txt
urlrelay.egg-info/dependency_links.txt
urlrelay.egg-info/top_level.txt
urlrelay.egg-info/zip-safe