Metadata-Version: 1.0
Name: urlrelay
Version: 0.7.1
Summary: RESTful WSGI URL dispatcher.
Home-page: UNKNOWN
Author: L. C. Rees
Author-email: lcrees@gmail.com
License: BSD
Keywords: WSGI URL dispatch relay route middleware web HTTP
Platform: UNKNOWN
Classifier: Development Status :: 4 - Beta
Classifier: Environment :: Web Environment
Classifier: License :: OSI Approved :: BSD License
Classifier: Natural Language :: English
Classifier: Operating System :: OS Independent
Classifier: Programming Language :: Python
Classifier: Topic :: Internet :: WWW/HTTP :: Dynamic Content
Classifier: Topic :: Internet :: WWW/HTTP :: Site Management
Classifier: Topic :: Internet :: WWW/HTTP :: WSGI :: Middleware
